{
    "1": {
        "index": "1",
        " country": "United States",
        " cases": "927150",
        " dead": "52400",
        " recovered": "101315"
    },
    "2": {
        "index": "2",
        " country": "Spain",
        " cases": "219764",
        " dead": "22524",
        " recovered": "92355"
    },
    "3": {
        "index": "3",
        " country": "Italy",
        " cases": "192994",
        " dead": "25969",
        " recovered": "60498"
    },
    "4": {
        "index": "4",
        " country": "Germany",
        " cases": "155054",
        " dead": "5767",
        " recovered": "99862"
    },
    "5": {
        "index": "5",
        " country": "United Kingdom",
        " cases": "143464",
        " dead": "19506",
        " recovered": "\u2014"
    },
    "6": {
        "index": "6",
        " country": "France",
        " cases": "122577",
        " dead": "22245",
        " recovered": "43493"
    },
    "7": {
        "index": "7",
        " country": "Turkey",
        " cases": "104912",
        " dead": "2600",
        " recovered": "21737"
    },
    "8": {
        "index": "8",
        " country": "Iran",
        " cases": "88194",
        " dead": "5574",
        " recovered": "66596"
    },
    "9": {
        "index": "9",
        " country": "China",
        " cases": "82816",
        " dead": "4632",
        " recovered": "77346"
    },
    "10": {
        "index": "10",
        " country": "Russia",
        " cases": "74588",
        " dead": "681",
        " recovered": "6250"
    },
    "11": {
        "index": "11",
        " country": "Brazil",
        " cases": "52995",
        " dead": "3670",
        " recovered": "26573"
    },
    "12": {
        "index": "12",
        " country": "Belgium",
        " cases": "45325",
        " dead": "6917",
        " recovered": "10417"
    },
    "13": {
        "index": "13",
        " country": "Canada",
        " cases": "43888",
        " dead": "2302",
        " recovered": "15541"
    },
    "14": {
        "index": "14",
        " country": "Netherlands",
        " cases": "36535",
        " dead": "4289",
        " recovered": "\u2014"
    },
    "15": {
        "index": "15",
        " country": "Switzerland",
        " cases": "28541",
        " dead": "1593",
        " recovered": "21000"
    },
    "16": {
        "index": "16",
        " country": "India",
        " cases": "24506",
        " dead": "775",
        " recovered": "5063"
    },
    "17": {
        "index": "17",
        " country": "Portugal",
        " cases": "22797",
        " dead": "854",
        " recovered": "1228"
    },
    "18": {
        "index": "18",
        " country": "Ecuador",
        " cases": "22719",
        " dead": "576",
        " recovered": "1366"
    },
    "19": {
        "index": "19",
        " country": "Peru",
        " cases": "21648",
        " dead": "634",
        " recovered": "7496"
    },
    "20": {
        "index": "20",
        " country": "Ireland",
        " cases": "18184",
        " dead": "1014",
        " recovered": "9233"
    },
    "21": {
        "index": "21",
        " country": "Sweden",
        " cases": "17567",
        " dead": "2152",
        " recovered": "550"
    },
    "22": {
        "index": "22",
        " country": "Israel",
        " cases": "15148",
        " dead": "198",
        " recovered": "6159"
    },
    "23": {
        "index": "23",
        " country": "Saudi Arabia",
        " cases": "15102",
        " dead": "127",
        " recovered": "2049"
    },
    "24": {
        "index": "24",
        " country": "Austria",
        " cases": "15068",
        " dead": "530",
        " recovered": "11872"
    },
    "25": {
        "index": "25",
        " country": "Japan",
        " cases": "13050",
        " dead": "348",
        " recovered": "2536"
    },
    "26": {
        "index": "26",
        " country": "Mexico",
        " cases": "12872",
        " dead": "1221",
        " recovered": "2627"
    },
    "27": {
        "index": "27",
        " country": "Singapore",
        " cases": "12693",
        " dead": "12",
        " recovered": "956"
    },
    "28": {
        "index": "28",
        " country": "Chile",
        " cases": "12306",
        " dead": "174",
        " recovered": "6327"
    },
    "29": {
        "index": "29",
        " country": "Pakistan",
        " cases": "11940",
        " dead": "253",
        " recovered": "2755"
    },
    "30": {
        "index": "30",
        " country": "Poland",
        " cases": "11067",
        " dead": "499",
        " recovered": "2126"
    },
    "31": {
        "index": "31",
        " country": "South Korea",
        " cases": "10718",
        " dead": "240",
        " recovered": "8635"
    },
    "32": {
        "index": "32",
        " country": "Romania",
        " cases": "10417",
        " dead": "552",
        " recovered": "2817"
    },
    "33": {
        "index": "33",
        " country": "Belarus",
        " cases": "9590",
        " dead": "67",
        " recovered": "1573"
    },
    "34": {
        "index": "34",
        " country": "United Arab Emirates",
        " cases": "9281",
        " dead": "64",
        " recovered": "1760"
    },
    "35": {
        "index": "35",
        " country": "Indonesia",
        " cases": "8607",
        " dead": "720",
        " recovered": "1042"
    },
    "36": {
        "index": "36",
        " country": "Qatar",
        " cases": "8525",
        " dead": "10",
        " recovered": "809"
    },
    "37": {
        "index": "37",
        " country": "Denmark",
        " cases": "8210",
        " dead": "403",
        " recovered": "5526"
    },
    "38": {
        "index": "38",
        " country": "Ukraine",
        " cases": "8125",
        " dead": "201",
        " recovered": "782"
    },
    "39": {
        "index": "39",
        " country": "Serbia",
        " cases": "7483",
        " dead": "144",
        " recovered": "1094"
    },
    "40": {
        "index": "40",
        " country": "Norway",
        " cases": "7463",
        " dead": "199",
        " recovered": "\u2014"
    },
    "41": {
        "index": "41",
        " country": "Philippines",
        " cases": "7294",
        " dead": "494",
        " recovered": "792"
    },
    "42": {
        "index": "42",
        " country": "Czech Republic",
        " cases": "7273",
        " dead": "215",
        " recovered": "2389"
    },
    "43": {
        "index": "43",
        " country": "Australia",
        " cases": "6695",
        " dead": "80",
        " recovered": "5372"
    },
    "44": {
        "index": "44",
        " country": "Dominican Republic",
        " cases": "5749",
        " dead": "267",
        " recovered": "763"
    },
    "45": {
        "index": "45",
        " country": "Malaysia",
        " cases": "5742",
        " dead": "98",
        " recovered": "3762"
    },
    "46": {
        "index": "46",
        " country": "Panama",
        " cases": "5338",
        " dead": "154",
        " recovered": "319"
    },
    "47": {
        "index": "47",
        " country": "Bangladesh",
        " cases": "4998",
        " dead": "140",
        " recovered": "112"
    },
    "48": {
        "index": "48",
        " country": "Colombia",
        " cases": "4881",
        " dead": "225",
        " recovered": "1003"
    },
    "49": {
        "index": "49",
        " country": "Finland",
        " cases": "4395",
        " dead": "177",
        " recovered": "2500"
    },
    "50": {
        "index": "50",
        " country": "South Africa",
        " cases": "4220",
        " dead": "79",
        " recovered": "1473"
    },
    "51": {
        "index": "51",
        " country": "Egypt",
        " cases": "4092",
        " dead": "294",
        " recovered": "1075"
    },
    "52": {
        "index": "52",
        " country": "Morocco",
        " cases": "3758",
        " dead": "158",
        " recovered": "486"
    },
    "53": {
        "index": "53",
        " country": "Luxembourg",
        " cases": "3695",
        " dead": "85",
        " recovered": "760"
    },
    "54": {
        "index": "54",
        " country": "Argentina",
        " cases": "3595",
        " dead": "176",
        " recovered": "965"
    },
    "55": {
        "index": "55",
        " country": "Algeria",
        " cases": "3127",
        " dead": "415",
        " recovered": "1408"
    },
    "56": {
        "index": "56",
        " country": "Moldova",
        " cases": "3110",
        " dead": "87",
        " recovered": "755"
    },
    "57": {
        "index": "57",
        " country": "Thailand",
        " cases": "2907",
        " dead": "51",
        " recovered": "2547"
    },
    "58": {
        "index": "58",
        " country": "Kuwait",
        " cases": "2614",
        " dead": "15",
        " recovered": "613"
    },
    "59": {
        "index": "59",
        " country": "Kazakhstan",
        " cases": "2525",
        " dead": "25",
        " recovered": "629"
    },
    "60": {
        "index": "60",
        " country": "Bahrain",
        " cases": "2518",
        " dead": "8",
        " recovered": "1113"
    },
    "61": {
        "index": "61",
        " country": "Greece",
        " cases": "2490",
        " dead": "130",
        " recovered": "577"
    },
    "62": {
        "index": "62",
        " country": "Hungary",
        " cases": "2443",
        " dead": "262",
        " recovered": "458"
    },
    "63": {
        "index": "63",
        " country": "Croatia",
        " cases": "2009",
        " dead": "51",
        " recovered": "982"
    },
    "64": {
        "index": "64",
        " country": "Oman",
        " cases": "1905",
        " dead": "10",
        " recovered": "329"
    },
    "65": {
        "index": "65",
        " country": "Uzbekistan",
        " cases": "1836",
        " dead": "8",
        " recovered": "689"
    },
    "66": {
        "index": "66",
        " country": "Iceland",
        " cases": "1789",
        " dead": "10",
        " recovered": "1509"
    },
    "67": {
        "index": "67",
        " country": "Iraq",
        " cases": "1708",
        " dead": "86",
        " recovered": "1204"
    },
    "68": {
        "index": "68",
        " country": "Armenia",
        " cases": "1677",
        " dead": "28",
        " recovered": "803"
    },
    "69": {
        "index": "69",
        " country": "Estonia",
        " cases": "1605",
        " dead": "46",
        " recovered": "184"
    },
    "70": {
        "index": "70",
        " country": "Azerbaijan",
        " cases": "1592",
        " dead": "21",
        " recovered": "1013"
    },
    "71": {
        "index": "71",
        " country": "Afghanistan",
        " cases": "1463",
        " dead": "47",
        " recovered": "206"
    },
    "72": {
        "index": "72",
        " country": "Cameroon",
        " cases": "1430",
        " dead": "43",
        " recovered": "668"
    },
    "73": {
        "index": "73",
        " country": "Lithuania",
        " cases": "1426",
        " dead": "41",
        " recovered": "460"
    },
    "74": {
        "index": "74",
        " country": "Bosnia & Herzegovina",
        " cases": "1421",
        " dead": "55",
        " recovered": "538"
    },
    "75": {
        "index": "75",
        " country": "Slovenia",
        " cases": "1373",
        " dead": "80",
        " recovered": "211"
    },
    "76": {
        "index": "76",
        " country": "Slovakia",
        " cases": "1360",
        " dead": "17",
        " recovered": "355"
    },
    "77": {
        "index": "77",
        " country": "North Macedonia",
        " cases": "1326",
        " dead": "57",
        " recovered": "337"
    },
    "78": {
        "index": "78",
        " country": "Cuba",
        " cases": "1285",
        " dead": "49",
        " recovered": "416"
    },
    "79": {
        "index": "79",
        " country": "Ghana",
        " cases": "1279",
        " dead": "10",
        " recovered": "134"
    },
    "80": {
        "index": "80",
        " country": "Puerto Rico",
        " cases": "1276",
        " dead": "77",
        " recovered": "\u2014"
    },
    "81": {
        "index": "81",
        " country": "Bulgaria",
        " cases": "1188",
        " dead": "54",
        " recovered": "193"
    },
    "82": {
        "index": "82",
        " country": "New Zealand",
        " cases": "1117",
        " dead": "18",
        " recovered": "1118"
    },
    "83": {
        "index": "83",
        " country": "Nigeria",
        " cases": "1095",
        " dead": "32",
        " recovered": "208"
    },
    "84": {
        "index": "84",
        " country": "Ivory Coast",
        " cases": "1077",
        " dead": "14",
        " recovered": "419"
    },
    "85": {
        "index": "85",
        " country": "Hong Kong",
        " cases": "1036",
        " dead": "4",
        " recovered": "725"
    },
    "86": {
        "index": "86",
        " country": "Djibouti",
        " cases": "999",
        " dead": "2",
        " recovered": "330"
    },
    "87": {
        "index": "87",
        " country": "Guinea",
        " cases": "954",
        " dead": "6",
        " recovered": "191"
    },
    "88": {
        "index": "88",
        " country": "Tunisia",
        " cases": "922",
        " dead": "38",
        " recovered": "194"
    },
    "89": {
        "index": "89",
        " country": "Bolivia",
        " cases": "807",
        " dead": "44",
        " recovered": "54"
    },
    "90": {
        "index": "90",
        " country": "Cyprus",
        " cases": "804",
        " dead": "14",
        " recovered": "98"
    },
    "91": {
        "index": "91",
        " country": "Latvia",
        " cases": "784",
        " dead": "12",
        " recovered": "133"
    },
    "92": {
        "index": "92",
        " country": "Andorra",
        " cases": "731",
        " dead": "40",
        " recovered": "344"
    },
    "93": {
        "index": "93",
        " country": "Kosovo",
        " cases": "703",
        " dead": "19",
        " recovered": "162"
    },
    "94": {
        "index": "94",
        " country": "Lebanon",
        " cases": "696",
        " dead": "22",
        " recovered": "140"
    },
    "95": {
        "index": "95",
        " country": "Costa Rica",
        " cases": "687",
        " dead": "6",
        " recovered": "196"
    },
    "96": {
        "index": "96",
        " country": "Niger",
        " cases": "681",
        " dead": "24",
        " recovered": "289"
    },
    "97": {
        "index": "97",
        " country": "Albania",
        " cases": "678",
        " dead": "27",
        " recovered": "394"
    },
    "98": {
        "index": "98",
        " country": "Kyrgyzstan",
        " cases": "665",
        " dead": "8",
        " recovered": "345"
    },
    "99": {
        "index": "99",
        " country": "Burkina Faso",
        " cases": "629",
        " dead": "41",
        " recovered": "425"
    },
    "100": {
        "index": "100",
        " country": "Uruguay",
        " cases": "563",
        " dead": "12",
        " recovered": "369"
    },
    "101": {
        "index": "101",
        " country": "Honduras",
        " cases": "591",
        " dead": "55",
        " recovered": "58"
    },
    "102": {
        "index": "102",
        " country": "Senegal",
        " cases": "545",
        " dead": "6",
        " recovered": "262"
    },
    "103": {
        "index": "103",
        " country": "San Marino",
        " cases": "513",
        " dead": "40",
        " recovered": "64"
    },
    "104": {
        "index": "104",
        " country": "Malta",
        " cases": "447",
        " dead": "3",
        " recovered": "223"
    },
    "105": {
        "index": "105",
        " country": "Georgia",
        " cases": "444",
        " dead": "5",
        " recovered": "132"
    },
    "106": {
        "index": "106",
        " country": "Jordan",
        " cases": "441",
        " dead": "7",
        " recovered": "326"
    },
    "107": {
        "index": "107",
        " country": "Guatemala",
        " cases": "430",
        " dead": "11",
        " recovered": "30"
    },
    "108": {
        "index": "108",
        " country": "Taiwan",
        " cases": "429",
        " dead": "6",
        " recovered": "275"
    },
    "109": {
        "index": "109",
        " country": "Sri Lanka",
        " cases": "420",
        " dead": "7",
        " recovered": "109"
    },
    "110": {
        "index": "110",
        " country": "DR Congo",
        " cases": "416",
        " dead": "28",
        " recovered": "49"
    },
    "111": {
        "index": "111",
        " country": "Palestine",
        " cases": "339",
        " dead": "2",
        " recovered": "91"
    },
    "112": {
        "index": "112",
        " country": "Kenya",
        " cases": "336",
        " dead": "14",
        " recovered": "95"
    },
    "113": {
        "index": "113",
        " country": "Mauritius",
        " cases": "331",
        " dead": "9",
        " recovered": "285"
    },
    "114": {
        "index": "114",
        " country": "Somalia",
        " cases": "328",
        " dead": "16",
        " recovered": "8"
    },
    "115": {
        "index": "115",
        " country": "Mali",
        " cases": "325",
        " dead": "21",
        " recovered": "87"
    },
    "116": {
        "index": "116",
        " country": "Montenegro",
        " cases": "319",
        " dead": "6",
        " recovered": "123"
    },
    "117": {
        "index": "117",
        " country": "Venezuela",
        " cases": "318",
        " dead": "10",
        " recovered": "128"
    },
    "118": {
        "index": "118",
        " country": "Isle of Man",
        " cases": "308",
        " dead": "18",
        " recovered": "230"
    },
    "119": {
        "index": "119",
        " country": "Jamaica",
        " cases": "288",
        " dead": "7",
        " recovered": "28"
    },
    "120": {
        "index": "120",
        " country": "Tanzania",
        " cases": "284",
        " dead": "10",
        " recovered": "11"
    },
    "121": {
        "index": "121",
        " country": "Jersey",
        " cases": "278",
        " dead": "19",
        " recovered": "165"
    },
    "122": {
        "index": "122",
        " country": "Vietnam",
        " cases": "270",
        " dead": "0",
        " recovered": "225"
    },
    "123": {
        "index": "123",
        " country": "El Salvador",
        " cases": "261",
        " dead": "8",
        " recovered": "72"
    },
    "124": {
        "index": "124",
        " country": "Guernsey",
        " cases": "245",
        " dead": "11",
        " recovered": "155"
    },
    "125": {
        "index": "125",
        " country": "Paraguay",
        " cases": "223",
        " dead": "9",
        " recovered": "78"
    },
    "126": {
        "index": "126",
        " country": "Equatorial Guinea",
        " cases": "214",
        " dead": "1",
        " recovered": "7"
    },
    "127": {
        "index": "127",
        " country": "Republic of the Congo",
        " cases": "200",
        " dead": "6",
        " recovered": "19"
    },
    "128": {
        "index": "128",
        " country": "Faroe Islands",
        " cases": "187",
        " dead": "0",
        " recovered": "178"
    },
    "129": {
        "index": "129",
        " country": "Rwanda",
        " cases": "176",
        " dead": "0",
        " recovered": "87"
    },
    "130": {
        "index": "130",
        " country": "Sudan",
        " cases": "174",
        " dead": "16",
        " recovered": "14"
    },
    "131": {
        "index": "131",
        " country": "Gabon",
        " cases": "174",
        " dead": "3",
        " recovered": "26"
    },
    "132": {
        "index": "132",
        " country": "Myanmar",
        " cases": "144",
        " dead": "5",
        " recovered": "9"
    },
    "133": {
        "index": "133",
        " country": "Brunei",
        " cases": "138",
        " dead": "1",
        " recovered": "120"
    },
    "134": {
        "index": "134",
        " country": "Guam",
        " cases": "138",
        " dead": "5",
        " recovered": "126"
    },
    "135": {
        "index": "135",
        " country": "Gibraltar",
        " cases": "133",
        " dead": "0",
        " recovered": "131"
    },
    "136": {
        "index": "136",
        " country": "Maldives",
        " cases": "128",
        " dead": "0",
        " recovered": "16"
    },
    "137": {
        "index": "137",
        " country": "Cambodia",
        " cases": "122",
        " dead": "0",
        " recovered": "117"
    },
    "138": {
        "index": "138",
        " country": "Madagascar",
        " cases": "122",
        " dead": "0",
        " recovered": "61"
    },
    "139": {
        "index": "139",
        " country": "Ethiopia",
        " cases": "117",
        " dead": "3",
        " recovered": "25"
    },
    "140": {
        "index": "140",
        " country": "Liberia",
        " cases": "117",
        " dead": "8",
        " recovered": "25"
    },
    "141": {
        "index": "141",
        " country": "Trinidad & Tobago",
        " cases": "115",
        " dead": "8",
        " recovered": "45"
    },
    "142": {
        "index": "142",
        " country": "Northern Cyprus",
        " cases": "108",
        " dead": "3",
        " recovered": "52"
    },
    "143": {
        "index": "143",
        " country": "Aruba",
        " cases": "100",
        " dead": "2",
        " recovered": "69"
    },
    "144": {
        "index": "144",
        " country": "Bermuda",
        " cases": "99",
        " dead": "5",
        " recovered": "39"
    },
    "145": {
        "index": "145",
        " country": "Monaco",
        " cases": "94",
        " dead": "4",
        " recovered": "35"
    },
    "146": {
        "index": "146",
        " country": "Togo",
        " cases": "90",
        " dead": "6",
        " recovered": "59"
    },
    "147": {
        "index": "147",
        " country": "Cape Verde",
        " cases": "88",
        " dead": "1",
        " recovered": "1"
    },
    "148": {
        "index": "148",
        " country": "Zambia",
        " cases": "84",
        " dead": "3",
        " recovered": "37"
    },
    "149": {
        "index": "149",
        " country": "Liechtenstein",
        " cases": "82",
        " dead": "1",
        " recovered": "55"
    },
    "150": {
        "index": "150",
        " country": "Sierra Leone",
        " cases": "82",
        " dead": "3",
        " recovered": "10"
    },
    "151": {
        "index": "151",
        " country": "Barbados",
        " cases": "77",
        " dead": "6",
        " recovered": "31"
    },
    "152": {
        "index": "152",
        " country": "Uganda",
        " cases": "75",
        " dead": "0",
        " recovered": "46"
    },
    "153": {
        "index": "153",
        " country": "Bahamas",
        " cases": "73",
        " dead": "11",
        " recovered": "15"
    },
    "154": {
        "index": "154",
        " country": "Guyana",
        " cases": "73",
        " dead": "8",
        " recovered": "12"
    },
    "155": {
        "index": "155",
        " country": "Sint Maarten",
        " cases": "73",
        " dead": "12",
        " recovered": "22"
    },
    "156": {
        "index": "156",
        " country": "Haiti",
        " cases": "72",
        " dead": "5",
        " recovered": "2"
    },
    "157": {
        "index": "157",
        " country": "Cayman Islands",
        " cases": "70",
        " dead": "1",
        " recovered": "8"
    },
    "158": {
        "index": "158",
        " country": "Donetsk PR",
        " cases": "67",
        " dead": "1",
        " recovered": "2"
    },
    "159": {
        "index": "159",
        " country": "Libya",
        " cases": "61",
        " dead": "2",
        " recovered": "18"
    },
    "160": {
        "index": "160",
        " country": "French Polynesia",
        " cases": "57",
        " dead": "0",
        " recovered": "35"
    },
    "161": {
        "index": "161",
        " country": "Benin",
        " cases": "54",
        " dead": "1",
        " recovered": "27"
    },
    "162": {
        "index": "162",
        " country": "U.S. Virgin Islands",
        " cases": "54",
        " dead": "3",
        " recovered": "50"
    },
    "163": {
        "index": "163",
        " country": "Guinea-Bissau",
        " cases": "52",
        " dead": "0",
        " recovered": "3"
    },
    "164": {
        "index": "164",
        " country": "Nepal",
        " cases": "48",
        " dead": "0",
        " recovered": "10"
    },
    "165": {
        "index": "165",
        " country": "Luhansk PR",
        " cases": "48",
        " dead": "0",
        " recovered": "7"
    },
    "166": {
        "index": "166",
        " country": "Mozambique",
        " cases": "46",
        " dead": "0",
        " recovered": "9"
    },
    "167": {
        "index": "167",
        " country": "Macau",
        " cases": "45",
        " dead": "0",
        " recovered": "27"
    },
    "168": {
        "index": "168",
        " country": "Syria",
        " cases": "42",
        " dead": "3",
        " recovered": "6"
    },
    "169": {
        "index": "169",
        " country": "Chad",
        " cases": "40",
        " dead": "0",
        " recovered": "8"
    },
    "170": {
        "index": "170",
        " country": "Eswatini",
        " cases": "40",
        " dead": "1",
        " recovered": "10"
    },
    "171": {
        "index": "171",
        " country": "Eritrea",
        " cases": "39",
        " dead": "0",
        " recovered": "11"
    },
    "172": {
        "index": "172",
        " country": "Mongolia",
        " cases": "36",
        " dead": "0",
        " recovered": "9"
    },
    "173": {
        "index": "173",
        " country": "Malawi",
        " cases": "33",
        " dead": "3",
        " recovered": "4"
    },
    "174": {
        "index": "174",
        " country": "Zimbabwe",
        " cases": "29",
        " dead": "4",
        " recovered": "2"
    },
    "175": {
        "index": "175",
        " country": "Angola",
        " cases": "25",
        " dead": "2",
        " recovered": "6"
    },
    "176": {
        "index": "176",
        " country": "East Timor",
        " cases": "24",
        " dead": "0",
        " recovered": "2"
    },
    "177": {
        "index": "177",
        " country": "Antigua & Barbuda",
        " cases": "23",
        " dead": "3",
        " recovered": "3"
    },
    "178": {
        "index": "178",
        " country": "Botswana",
        " cases": "22",
        " dead": "1",
        " recovered": "0"
    },
    "179": {
        "index": "179",
        " country": "Laos",
        " cases": "19",
        " dead": "0",
        " recovered": "4"
    },
    "180": {
        "index": "180",
        " country": "Belize",
        " cases": "18",
        " dead": "2",
        " recovered": "5"
    },
    "181": {
        "index": "181",
        " country": "Fiji",
        " cases": "18",
        " dead": "0",
        " recovered": "10"
    },
    "182": {
        "index": "182",
        " country": "New Caledonia",
        " cases": "18",
        " dead": "0",
        " recovered": "17"
    },
    "183": {
        "index": "183",
        " country": "Central African Republic",
        " cases": "16",
        " dead": "0",
        " recovered": "10"
    },
    "184": {
        "index": "184",
        " country": "Cura\u00e7ao",
        " cases": "16",
        " dead": "1",
        " recovered": "12"
    },
    "185": {
        "index": "185",
        " country": "Dominica",
        " cases": "16",
        " dead": "0",
        " recovered": "9"
    },
    "186": {
        "index": "186",
        " country": "Namibia",
        " cases": "16",
        " dead": "0",
        " recovered": "7"
    },
    "187": {
        "index": "187",
        " country": "Grenada",
        " cases": "15",
        " dead": "0",
        " recovered": "7"
    },
    "188": {
        "index": "188",
        " country": "Saint Kitts & Nevis",
        " cases": "15",
        " dead": "0",
        " recovered": "2"
    },
    "189": {
        "index": "189",
        " country": "Saint Lucia",
        " cases": "15",
        " dead": "0",
        " recovered": "15"
    },
    "190": {
        "index": "190",
        " country": "Northern Mariana Islands ",
        " cases": "14",
        " dead": "2",
        " recovered": "11"
    },
    "191": {
        "index": "191",
        " country": "Saint Vincent",
        " cases": "14",
        " dead": "0",
        " recovered": "5"
    },
    "192": {
        "index": "192",
        " country": "Falkland Islands",
        " cases": "13",
        " dead": "0",
        " recovered": "11"
    },
    "193": {
        "index": "193",
        " country": "\u00c5land Islands",
        " cases": "11",
        " dead": "0",
        " recovered": "0"
    },
    "194": {
        "index": "194",
        " country": "Burundi",
        " cases": "11",
        " dead": "1",
        " recovered": "4"
    },
    "195": {
        "index": "195",
        " country": "Greenland",
        " cases": "11",
        " dead": "0",
        " recovered": "11"
    },
    "196": {
        "index": "196",
        " country": "Montserrat",
        " cases": "11",
        " dead": "0",
        " recovered": "2"
    },
    "197": {
        "index": "197",
        " country": "Nicaragua",
        " cases": "11",
        " dead": "3",
        " recovered": "7"
    },
    "198": {
        "index": "198",
        " country": "Seychelles",
        " cases": "11",
        " dead": "0",
        " recovered": "7"
    },
    "199": {
        "index": "199",
        " country": "Turks & Caicos Islands",
        " cases": "11",
        " dead": "1",
        " recovered": "4"
    },
    "200": {
        "index": "200",
        " country": "The Gambia",
        " cases": "10",
        " dead": "1",
        " recovered": "6"
    },
    "201": {
        "index": "201",
        " country": "Suriname",
        " cases": "10",
        " dead": "1",
        " recovered": "7"
    },
    "202": {
        "index": "202",
        " country": "Vatican City",
        " cases": "9",
        " dead": "0",
        " recovered": "2"
    },
    "203": {
        "index": "203",
        " country": "Papua New Guinea",
        " cases": "8",
        " dead": "0",
        " recovered": "0"
    },
    "204": {
        "index": "204",
        " country": "Artsakh",
        " cases": "7",
        " dead": "0",
        " recovered": "0"
    },
    "205": {
        "index": "205",
        " country": "Bhutan",
        " cases": "7",
        " dead": "0",
        " recovered": "3"
    },
    "206": {
        "index": "206",
        " country": "Mauritania",
        " cases": "7",
        " dead": "1",
        " recovered": "6"
    },
    "207": {
        "index": "207",
        " country": "Somaliland",
        " cases": "6",
        " dead": "0",
        " recovered": "1"
    },
    "208": {
        "index": "208",
        " country": "South Sudan",
        " cases": "5",
        " dead": "0",
        " recovered": "0"
    },
    "209": {
        "index": "209",
        " country": "British Virgin Islands",
        " cases": "4",
        " dead": "1",
        " recovered": "2"
    },
    "210": {
        "index": "210",
        " country": "S\u00e3o Tom\u00e9 & Pr\u00edncipe",
        " cases": "4",
        " dead": "0",
        " recovered": "0"
    },
    "211": {
        "index": "211",
        " country": "Abkhazia",
        " cases": "3",
        " dead": "0",
        " recovered": "1"
    },
    "212": {
        "index": "212",
        " country": "Anguilla",
        " cases": "3",
        " dead": "0",
        " recovered": "1"
    },
    "213": {
        "index": "213",
        " country": "Bonaire",
        " cases": "2",
        " dead": "0",
        " recovered": "1"
    },
    "214": {
        "index": "214",
        " country": "Saba",
        " cases": "2",
        " dead": "0",
        " recovered": "0"
    },
    "215": {
        "index": "215",
        " country": "Sint Eustatius",
        " cases": "2",
        " dead": "0",
        " recovered": "1"
    },
    "216": {
        "index": "216",
        " country": "Guantanamo Bay",
        " cases": "1",
        " dead": "0",
        " recovered": "\u2014"
    },
    "217": {
        "index": "217",
        " country": "Saint Pierre & Miquelon",
        " cases": "1",
        " dead": "0",
        " recovered": "0"
    },
    "218": {
        "index": "218",
        " country": "Yemen",
        " cases": "1",
        " dead": "0",
        " recovered": "1"
    }
}